{ "events":[
    {
        "id": "1",
        "name": "Application Submitted",
        "date": "2020-04-01",
        "description": "Application submitted to the timeline",
        "category": "Application",
        "iconUrl": "mdi-account-file-text",
        "pairEventId": "1",
        "eventType": "paired",
        "status": "started",
        "estimatedCompleteDate": "2020-05-01"
    },    
    {
        "id": "2",
        "name": "Medical Records Requested",
        "date": "2020-05-01",
        "description": "Medical records submitted to the timeline",
        "category": "Application",
        "iconUrl": "mdi-application-import",
        "pairEventId": "1",
        "eventType": "paired",
        "status": "completed",
        "estimatedCompleteDate": null
    },
    {   
        "id": "3",
        "name": "Medical Records Received",
        "date": "2020-08-02",
        "description": "Medical records received to the timeline",
        "category": "Application",
        "iconUrl": "mdi-database-plus-outline",
        "pairEventId": null,
        "eventType": "single",
        "status": "completed",
        "estimatedCompleteDate": null
    },
    {
        "id": "4",
        "name": "Decision Date",
        "date": "2020-10-02",
        "description": "Decision date to the timeline",
        "category": "Application",
        "iconUrl": "mdi-arrow-decision",
        "pairEventId": null,
        "eventType": "single",
        "status": "completed",
        "estimatedCompleteDate": null
  
    },
    {
        "id": "5",
        "name": "Evaluation Started",
        "date": "2021-04-02",
        "description": "Evaluation started to the timeline",
        "category": "Evaluation",
        "iconUrl": "mdi-clock-start",
        "pairEventId": "2",
        "eventType": "paired",
        "status": "started",
        "estimatedCompleteDate": "2021-07-15"
  
    },
    {
        "id": "6",
        "name": "Evaluation Completed",
        "date": "2021-07-15",
        "description": "Evaluation completed to the timeline",
        "category": "Evaluation",
        "iconUrl": "mdi-file-chart-check-outline",
        "pairEventId": "2",
        "eventType": "paired",
        "status": "completed",
        "estimatedCompleteDate": null
  
    },
    {   
        "id": "7",
        "name": "Wrap Up Documents",
        "date": "2021-09-15",
        "description": "Wrap up docs to the timeline",
        "category": "Post Wrap Up",
        "iconUrl": "mdi-download-box-outline",
        "pairEventId": null,
        "eventType": "single",
        "status": "completed",
        "estimatedCompleteDate": null
  
    }

   
     
]}